dptb/__init__.py
dptb/__main__.py
dptb/data/AtomicData.py
dptb/data/AtomicDataDict.py
dptb/data/__init__.py
dptb/data/_keys.py
dptb/data/build.py
dptb/data/dataloader.py
dptb/data/dataset/__init__.py
dptb/data/dataset/_abacus_dataset.py
dptb/data/dataset/_abacus_dataset_mem.py
dptb/data/dataset/_ase_dataset.py
dptb/data/dataset/_base_datasets.py
dptb/data/dataset/_deeph_dataset.py
dptb/data/dataset/_default_dataset.py
dptb/data/dataset/_hdf5_dataset.py
dptb/data/dataset/_npz_dataset.py
dptb/data/dataset/lmdb_dataset.py
dptb/data/interfaces/__init__.py
dptb/data/interfaces/abacus.py
dptb/data/interfaces/ham_to_feature.py
dptb/data/interfaces/pyscf.py
dptb/data/test_data.py
dptb/data/transforms.py
dptb/data/use_data.ipynb
dptb/data/util.py
dptb/entrypoints/__init__.py
dptb/entrypoints/bond.py
dptb/entrypoints/collectskf.py
dptb/entrypoints/config.py
dptb/entrypoints/data.py
dptb/entrypoints/emp_sk.py
dptb/entrypoints/main.py
dptb/entrypoints/nrl2json.py
dptb/entrypoints/pth2json.py
dptb/entrypoints/run.py
dptb/entrypoints/test.py
dptb/entrypoints/train.py
dptb/negf/__init__.py
dptb/negf/areshkin_pole_sum.py
dptb/negf/density.py
dptb/negf/device_property.py
dptb/negf/field.py
dptb/negf/lead_property.py
dptb/negf/negf_hamiltonian_init.py
dptb/negf/negf_utils.py
dptb/negf/ozaki_res_cal.py
dptb/negf/recursive_green_cal.py
dptb/negf/scf_method.py
dptb/negf/sgf.py
dptb/negf/surface_green.py
dptb/negf/transport.py
dptb/nn/Jd.pt
dptb/nn/__init__.py
dptb/nn/base.py
dptb/nn/build.py
dptb/nn/cutoff.py
dptb/nn/deeptb.py
dptb/nn/dftb/__init__.py
dptb/nn/dftb/base_poly2.pth
dptb/nn/dftb/base_poly4.pth
dptb/nn/dftb/hopping_dftb.py
dptb/nn/dftb/sk_param.py
dptb/nn/dftb2nnsk.py
dptb/nn/dftb2nnsk_bak.py
dptb/nn/dftbsk.py
dptb/nn/embedding/__init__.py
dptb/nn/embedding/baseline.py
dptb/nn/embedding/deephe3.py
dptb/nn/embedding/e3baseline_local6.py
dptb/nn/embedding/e3baseline_nonlocal.py
dptb/nn/embedding/emb.py
dptb/nn/embedding/from_deephe3/__init__.py
dptb-2.2.0.dist-info/LICENSE
dptb-2.2.0.dist-info/METADATA
dptb-2.2.0.dist-info/WHEEL
dptb-2.2.0.dist-info/entry_points.txt
dptb-2.2.0.dist-info/RECORD
