Metadata-Version: 2.3
Name: dptb
Version: 2.2.0
Summary: A unified deep learning package for electronic structure models including tight-binding, KS Hamiltonian and density matrix models
License: LGPL-3.0
Requires-Python: >=3.9,<=3.12.9
Classifier: License :: OSI Approved :: GNU Lesser General Public License v3 (LGPLv3)
Classifier: Programming Language :: Python :: 3
Classifier: Programming Language :: Python :: 3.9
Classifier: Programming Language :: Python :: 3.10
Classifier: Programming Language :: Python :: 3.11
Classifier: Programming Language :: Python :: 3.12
Requires-Dist: ase
Requires-Dist: dargs (==0.4.4)
Requires-Dist: e3nn (>=0.5.1)
Requires-Dist: future
Requires-Dist: h5py (>=3.7.0,<=3.11.0,!=3.10.0)
Requires-Dist: lmdb (==1.4.1)
Requires-Dist: matplotlib
Requires-Dist: numpy
Requires-Dist: opt-einsum (==3.3.0)
Requires-Dist: pyfiglet (==1.0.2)
Requires-Dist: pytest (>=7.2.0)
Requires-Dist: pytest-order (==1.2.0)
Requires-Dist: pyyaml
Requires-Dist: scipy (>=1.11,<=1.12)
Requires-Dist: seekpath
Requires-Dist: spglib
Requires-Dist: tensorboard
Requires-Dist: torch (>=2.0.0,<=2.5.1)
Requires-Dist: torch-runstats (==0.2.0)
Requires-Dist: torch_geometric (>=2.4.0)
Requires-Dist: torch_scatter (==2.1.2)
Requires-Dist: xitorch (==0.3.0)
Project-URL: Repository, https://github.com/deepmodeling/DeePTB
